avnst_util/__init__.py
avnst_util/config.py
avnst_util/teae_flag_deriver.py
avnst_util/time_alignment.py
avnst_util-0.1.dist-info/METADATA
avnst_util-0.1.dist-info/WHEEL
avnst_util-0.1.dist-info/top_level.txt
avnst_util-0.1.dist-info/RECORD
