Metadata-Version: 2.4
Name: avnst_util
Version: 0.1
Summary: Avansight Python utility package
Home-page: https://github.com/avansightinc/avnst_util
Author: Eric Liu
Author-email: eric.liu@avansightinc.com
Keywords: clinical trials,data analysis,time alignment,TEAE
Classifier: Development Status :: 3 - Alpha
Classifier: Intended Audience :: Science/Research
Classifier: Programming Language :: Python :: 3
Classifier: Programming Language :: Python :: 3.6
Classifier: Programming Language :: Python :: 3.7
Classifier: Programming Language :: Python :: 3.8
Classifier: Programming Language :: Python :: 3.9
Requires-Python: >=3.6
Requires-Dist: pandas>=1.0.0
Dynamic: author
Dynamic: author-email
Dynamic: classifier
Dynamic: description
Dynamic: description-content-type
Dynamic: home-page
Dynamic: keywords
Dynamic: requires-dist
Dynamic: requires-python
Dynamic: summary
